hindiExtract/__init__.py
hindiExtract/clean.py
hindiExtract/extract.py
textcleaner_hi-1.0.0.dist-info/LICENSE
textcleaner_hi-1.0.0.dist-info/METADATA
textcleaner_hi-1.0.0.dist-info/WHEEL
textcleaner_hi-1.0.0.dist-info/entry_points.txt
textcleaner_hi-1.0.0.dist-info/top_level.txt
textcleaner_hi-1.0.0.dist-info/RECORD
