Metadata-Version: 2.1
Name: textcleaner-hi
Version: 1.0.0
Summary: A Python package to extract hindi characters.
Home-page: UNKNOWN
Author: Chhavi Trivedi, Naman Jain, Ms. Gayatri Venugopal
Author-email: chhavi7320@gmail.com, n.jnamanjain2001@gmail.com, gayatrivenugopal3@gmail.com
License: MIT License
Platform: UNKNOWN
Classifier: License :: OSI Approved :: MIT License
Classifier: Programming Language :: Python :: 3
Classifier: Programming Language :: Python :: 3.7
